{
  "tables": {
    "only_in_old_db": [],
    "only_in_new_db": []
  },
  "table_changes": {
    "item_data": {
      "data_changes": {
        "added": [
          [["description", "據說能使琳德突破力量極限並更為提升的戒指。裝備後能使角色Lv突破極限並超越主角Lv。"], ["end_time", "2030/08/01 14:59:00"], ["gojuon_order", 0], ["item_id", 41277], ["item_name", "琳德專用戒指"], ["item_type", 22], ["limit_num", 9999], ["price", 0], ["promotion_level", 1], ["sell_check_disp", 0], ["start_time", "2015/12/17 15:00:00"], ["value", 0]],
          [["description", "封印有琳德的記憶碎片的道具。收集一定數量，則可以解放角色深藏的力量。"], ["end_time", "2030/08/01 14:59:59"], ["gojuon_order", 8194312], ["item_id", 31277], ["item_name", "琳德的記憶碎片"], ["item_type", 11], ["limit_num", 9999], ["price", 0], ["promotion_level", 1], ["sell_check_disp", 0], ["start_time", "2015/12/17 15:00:00"], ["value", 31277]]
        ]
      }
    },
    "emblem_data": {
      "data_changes": {
        "added": [
          [["description_mission_id", 56011905], ["disp_oder", 201899], ["emblem_id", 10201905], ["emblem_name", "琳德"], ["end_time", "2030/01/01 23:59:59"], ["event_emblem", 0], ["start_time", "2025/02/10 16:00:00"], ["type", 2]],
          [["description_mission_id", 56011906], ["disp_oder", 201900], ["emblem_id", 10201906], ["emblem_name", "與琳德的羈絆"], ["end_time", "2030/01/01 23:59:59"], ["event_emblem", 0], ["start_time", "2025/02/10 16:00:00"], ["type", 2]],
          [["description_mission_id", 56011907], ["disp_oder", 201901], ["emblem_id", 10201907], ["emblem_name", "加油琳德"], ["end_time", "2030/01/01 23:59:59"], ["event_emblem", 0], ["start_time", "2025/02/10 16:00:00"], ["type", 2]]
        ]
      }
    },
    "tips": {
      "data_changes": {
        "added": [
          [["id", 4127701], ["tips_index", 1], ["title", "全套服務"], ["value", 127701]]
        ]
      }
    },
    "story_detail": {
      "data_changes": {
        "added": [
          [["can_bookmark", 1], ["end_time", "2030/12/17 14:59:59"], ["force_unlock_time", "2030/12/17 14:59:59"], ["force_unlock_time_2", "2030/12/17 14:59:59"], ["lock_all_text", 0], ["love_level", 8], ["pre_story_id", 1277003], ["pre_story_id_2", 0], ["read_process_flag", 1], ["requirement_id", 127701], ["reward_id_1", 91002], ["reward_id_2", 0], ["reward_id_3", 0], ["reward_type_1", 8], ["reward_type_2", 0], ["reward_type_3", 0], ["reward_value_1", 50], ["reward_value_2", 0], ["reward_value_3", 0], ["start_time", "2015/04/01 15:00:00"], ["story_end", 0], ["story_group_id", 1277], ["story_id", 1277004], ["story_quest_id", 0], ["sub_title", "痴痴地等待著的女僕女孩"], ["title", "琳德 第4話"], ["unlock_quest_id", 0], ["visible_type", 0]],
          [["can_bookmark", 1], ["end_time", "2030/12/17 14:59:59"], ["force_unlock_time", "2030/12/17 14:59:59"], ["force_unlock_time_2", "2030/12/17 14:59:59"], ["lock_all_text", 0], ["love_level", 5], ["pre_story_id", 1277002], ["pre_story_id_2", 0], ["read_process_flag", 1], ["requirement_id", 127701], ["reward_id_1", 91002], ["reward_id_2", 0], ["reward_id_3", 0], ["reward_type_1", 8], ["reward_type_2", 0], ["reward_type_3", 0], ["reward_value_1", 20], ["reward_value_2", 0], ["reward_value_3", 0], ["start_time", "2015/04/01 15:00:00"], ["story_end", 0], ["story_group_id", 1277], ["story_id", 1277003], ["story_quest_id", 0], ["sub_title", "琳德的戰力提升作戰"], ["title", "琳德 第3話"], ["unlock_quest_id", 0], ["visible_type", 0]],
          [["can_bookmark", 1], ["end_time", "2030/12/17 14:59:59"], ["force_unlock_time", "2030/12/17 14:59:59"], ["force_unlock_time_2", "2030/12/17 14:59:59"], ["lock_all_text", 0], ["love_level", 4], ["pre_story_id", 1277001], ["pre_story_id_2", 0], ["read_process_flag", 1], ["requirement_id", 127701], ["reward_id_1", 91002], ["reward_id_2", 0], ["reward_id_3", 0], ["reward_type_1", 8], ["reward_type_2", 0], ["reward_type_3", 0], ["reward_value_1", 20], ["reward_value_2", 0], ["reward_value_3", 0], ["start_time", "2015/04/01 15:00:00"], ["story_end", 0], ["story_group_id", 1277], ["story_id", 1277002], ["story_quest_id", 0], ["sub_title", "女僕姊姊 in 蘭德索爾"], ["title", "琳德 第2話"], ["unlock_quest_id", 0], ["visible_type", 0]],
          [["can_bookmark", 1], ["end_time", "2030/12/17 14:59:59"], ["force_unlock_time", "2030/12/17 14:59:59"], ["force_unlock_time_2", "2030/12/17 14:59:59"], ["lock_all_text", 0], ["love_level", 0], ["pre_story_id", 2209009], ["pre_story_id_2", 0], ["read_process_flag", 1], ["requirement_id", 127701], ["reward_id_1", 91002], ["reward_id_2", 0], ["reward_id_3", 0], ["reward_type_1", 8], ["reward_type_2", 0], ["reward_type_3", 0], ["reward_value_1", 20], ["reward_value_2", 0], ["reward_value_3", 0], ["start_time", "2015/04/01 15:00:00"], ["story_end", 0], ["story_group_id", 1277], ["story_id", 1277001], ["story_quest_id", 0], ["sub_title", "洗濯工作與女僕的日常"], ["title", "琳德 第1話"], ["unlock_quest_id", 0], ["visible_type", 0]]
        ]
      }
    },
    "voice_group_chara": {
      "data_changes": {
        "added": [
          [["group_unit_id", 127701001], ["group_unit_id_comment", "琳德"], ["unit_id_01", 127701], ["unit_id_02", 0], ["unit_id_03", 0], ["unit_id_04", 0], ["unit_id_05", 0], ["unit_id_06", 0], ["unit_id_07", 0], ["unit_id_08", 0], ["unit_id_09", 0], ["unit_id_10", 0]]
        ]
      }
    },
    "unit_introduction": {
      "data_changes": {
        "added": [
          [["end_time", "2025/02/13 15:59:59"], ["gacha_id", 30349], ["id", 342], ["introduction_number", 1], ["maximum_chunk_size_1", 380000], ["maximum_chunk_size_2", 0], ["maximum_chunk_size_3", 0], ["maximum_chunk_size_loop_1", 380000], ["maximum_chunk_size_loop_2", 0], ["maximum_chunk_size_loop_3", 0], ["start_time", "2025/02/10 16:00:00"]],
          [["end_time", "2025/02/17 15:59:59"], ["gacha_id", 30350], ["id", 341], ["introduction_number", 1], ["maximum_chunk_size_1", 380000], ["maximum_chunk_size_2", 0], ["maximum_chunk_size_3", 0], ["maximum_chunk_size_loop_1", 380000], ["maximum_chunk_size_loop_2", 0], ["maximum_chunk_size_loop_3", 0], ["start_time", "2025/02/10 16:00:00"]]
        ]
      }
    },
    "unit_data": {
      "data_changes": {
        "added": [
          [["atk_type", 2], ["comment", "【魔法】位於後衛，為女僕工作四處奔走的龍人族雙胞胎姊姊。\\nＵＢ的領域展開時能再次發動攻擊、防禦、ＴＰ恢復等\\n多樣的支援技能效果來無微不至地支援我方。"], ["cutin1_star6", 127701], ["cutin2_star6", 0], ["cutin_1", 127701], ["cutin_2", 0], ["end_time", "2030/12/31 15:00:00"], ["exskill_display", 0], ["guild_id", 0], ["is_limited", 0], ["kana", "琳德"], ["motion_type", 48], ["move_speed", 450], ["normal_atk_cast_time", 1.965], ["only_disp_owned", 0], ["original_unit_id", 0], ["prefab_id", 127701], ["prefab_id_battle", 0], ["rarity", 3], ["se_type", 6], ["search_area_width", 693], ["start_time", "2025/02/10 16:00:00"], ["unit_id", 127701], ["unit_name", "琳德"]]
        ],
        "modified": [
          {
            "id": 127201,
            "old": [["atk_type", 2], ["comment", "【魔法】位於後衛，身穿制服、滿心期待的青春貓女。\\n除了支援攻守兩方面外，更能以提升行動速度和恢復TP\\n支援我方，並以UB攻擊距離最遠的敵人取得耀眼勝利。"], ["cutin1_star6", 127201], ["cutin2_star6", 0], ["cutin_1", 127201], ["cutin_2", 0], ["end_time", "2024/08/01 15:59:59"], ["exskill_display", 0], ["guild_id", 0], ["is_limited", 1], ["kana", "凱留（插班生）"], ["motion_type", 7], ["move_speed", 450], ["normal_atk_cast_time", 2.09], ["only_disp_owned", 0], ["original_unit_id", 0], ["prefab_id", 127201], ["prefab_id_battle", 0], ["rarity", 3], ["se_type", 7], ["search_area_width", 804], ["start_time", "2024/07/29 16:00:00"], ["unit_id", 127201], ["unit_name", "凱留（插班生）"]],
            "new": [["atk_type", 2], ["comment", "【魔法】位於後衛，身穿制服、滿心期待的青春貓女。\\n除了支援攻守兩方面外，更能以提升行動速度和恢復TP\\n支援我方，並以UB攻擊距離最遠的敵人取得耀眼勝利。"], ["cutin1_star6", 127201], ["cutin2_star6", 0], ["cutin_1", 127201], ["cutin_2", 0], ["end_time", "2025/02/13 15:59:59"], ["exskill_display", 0], ["guild_id", 0], ["is_limited", 1], ["kana", "凱留（插班生）"], ["motion_type", 7], ["move_speed", 450], ["normal_atk_cast_time", 2.09], ["only_disp_owned", 0], ["original_unit_id", 0], ["prefab_id", 127201], ["prefab_id_battle", 0], ["rarity", 3], ["se_type", 7], ["search_area_width", 804], ["start_time", "2025/02/10 16:00:00"], ["unit_id", 127201], ["unit_name", "凱留（插班生）"]]
          }
        ]
      }
    },
    "unit_enemy_data": {
      "data_changes": {
        "added": [
          [["atk_type", 2], ["comment", "有著琳德樣貌的特殊魔物"], ["cutin", 0], ["cutin_star6", 0], ["motion_type", 48], ["move_speed", 450], ["normal_atk_cast_time", 1.965], ["prefab_id", 127701], ["se_type", 6], ["search_area_width", 693], ["unit_id", 627701], ["unit_name", "琳德的闇影"], ["visual_change_flag", 1]]
        ]
      }
    },
    "banner": {
      "data_changes": {
        "added": [
          [["banner_id", 10305], ["condition_id", 0], ["end_date", "2025/02/13 15:59:59"], ["gacha_id", 30349], ["is_show_room", 0], ["priority", 19], ["start_date", "2025/02/10 16:00:00"], ["sub_banner_id_1", 0], ["system_id", 302], ["type", 1]],
          [["banner_id", 10306], ["condition_id", 0], ["end_date", "2025/02/17 15:59:59"], ["gacha_id", 30350], ["is_show_room", 0], ["priority", 18], ["start_date", "2025/02/10 16:00:00"], ["sub_banner_id_1", 0], ["system_id", 302], ["type", 1]]
        ],
        "modified": [
          {
            "id": 20032,
            "old": [["banner_id", 20032], ["condition_id", 0], ["end_date", "2025/01/26 15:59:59"], ["gacha_id", 0], ["is_show_room", 0], ["priority", 17], ["start_date", "2025/01/14 16:00:00"], ["sub_banner_id_1", 0], ["system_id", 305], ["type", 1]],
            "new": [["banner_id", 20032], ["condition_id", 0], ["end_date", "2025/02/17 15:59:59"], ["gacha_id", 0], ["is_show_room", 0], ["priority", 16], ["start_date", "2025/02/10 16:00:00"], ["sub_banner_id_1", 0], ["system_id", 305], ["type", 1]]
          }
        ]
      }
    },
    "unit_talent": {
      "data_changes": {
        "added": [
          [["setting_id", 12770101], ["talent_id", 1], ["unit_id", 127701]]
        ]
      }
    },
    "unlock_unit_condition": {
      "data_changes": {
        "added": [
          [["class_id", 1], ["condition_id_1", 31277], ["condition_id_2", 0], ["condition_id_3", 0], ["condition_id_4", 0], ["condition_id_5", 0], ["condition_type_1", 1], ["condition_type_2", 0], ["condition_type_3", 0], ["condition_type_4", 0], ["condition_type_5", 0], ["condition_type_detail_1", 2], ["condition_type_detail_2", 0], ["condition_type_detail_3", 0], ["condition_type_detail_4", 0], ["condition_type_detail_5", 0], ["count_1", 145], ["count_2", 0], ["count_3", 0], ["count_4", 0], ["count_5", 0], ["pre_unit_id", 0], ["release_effect_type", 2], ["unit_id", 127701], ["unit_name", "琳德"]]
        ]
      }
    },
    "unit_skill_data": {
      "data_changes": {
        "added": [
          [["ex_skill_1", 1277501], ["ex_skill_2", 0], ["ex_skill_3", 0], ["ex_skill_4", 0], ["ex_skill_5", 0], ["ex_skill_evolution_1", 1277511], ["ex_skill_evolution_2", 0], ["ex_skill_evolution_3", 0], ["ex_skill_evolution_4", 0], ["ex_skill_evolution_5", 0], ["main_skill_1", 1277002], ["main_skill_10", 0], ["main_skill_2", 1277003], ["main_skill_3", 0], ["main_skill_4", 0], ["main_skill_5", 0], ["main_skill_6", 0], ["main_skill_7", 0], ["main_skill_8", 0], ["main_skill_9", 0], ["main_skill_evolution_1", 0], ["main_skill_evolution_2", 0], ["sp_skill_1", 0], ["sp_skill_2", 0], ["sp_skill_3", 0], ["sp_skill_4", 0], ["sp_skill_5", 0], ["sp_skill_evolution_1", 0], ["sp_skill_evolution_2", 0], ["sp_union_burst", 0], ["union_burst", 1277001], ["union_burst_evolution", 0], ["unit_id", 127701]]
        ],
        "modified": [
          {
            "id": 127301,
            "old": [["ex_skill_1", 1273501], ["ex_skill_2", 0], ["ex_skill_3", 0], ["ex_skill_4", 0], ["ex_skill_5", 0], ["ex_skill_evolution_1", 1273511], ["ex_skill_evolution_2", 0], ["ex_skill_evolution_3", 0], ["ex_skill_evolution_4", 0], ["ex_skill_evolution_5", 0], ["main_skill_1", 1273002], ["main_skill_10", 0], ["main_skill_2", 1273003], ["main_skill_3", 0], ["main_skill_4", 0], ["main_skill_5", 0], ["main_skill_6", 0], ["main_skill_7", 0], ["main_skill_8", 0], ["main_skill_9", 0], ["main_skill_evolution_1", 0], ["main_skill_evolution_2", 0], ["sp_skill_1", 0], ["sp_skill_2", 0], ["sp_skill_3", 0], ["sp_skill_4", 0], ["sp_skill_5", 0], ["sp_skill_evolution_1", 0], ["sp_skill_evolution_2", 0], ["sp_union_burst", 0], ["union_burst", 1273001], ["union_burst_evolution", 0], ["unit_id", 127301]],
            "new": [["ex_skill_1", 1273501], ["ex_skill_2", 0], ["ex_skill_3", 0], ["ex_skill_4", 0], ["ex_skill_5", 0], ["ex_skill_evolution_1", 1273511], ["ex_skill_evolution_2", 0], ["ex_skill_evolution_3", 0], ["ex_skill_evolution_4", 0], ["ex_skill_evolution_5", 0], ["main_skill_1", 1273002], ["main_skill_10", 0], ["main_skill_2", 1273003], ["main_skill_3", 0], ["main_skill_4", 0], ["main_skill_5", 0], ["main_skill_6", 0], ["main_skill_7", 0], ["main_skill_8", 0], ["main_skill_9", 0], ["main_skill_evolution_1", 1273012], ["main_skill_evolution_2", 0], ["sp_skill_1", 0], ["sp_skill_2", 0], ["sp_skill_3", 0], ["sp_skill_4", 0], ["sp_skill_5", 0], ["sp_skill_evolution_1", 0], ["sp_skill_evolution_2", 0], ["sp_union_burst", 0], ["union_burst", 1273001], ["union_burst_evolution", 0], ["unit_id", 127301]]
          },
          {
            "id": 127201,
            "old": [["ex_skill_1", 1272501], ["ex_skill_2", 0], ["ex_skill_3", 0], ["ex_skill_4", 0], ["ex_skill_5", 0], ["ex_skill_evolution_1", 1272511], ["ex_skill_evolution_2", 0], ["ex_skill_evolution_3", 0], ["ex_skill_evolution_4", 0], ["ex_skill_evolution_5", 0], ["main_skill_1", 1272002], ["main_skill_10", 0], ["main_skill_2", 1272003], ["main_skill_3", 0], ["main_skill_4", 0], ["main_skill_5", 0], ["main_skill_6", 0], ["main_skill_7", 0], ["main_skill_8", 0], ["main_skill_9", 0], ["main_skill_evolution_1", 0], ["main_skill_evolution_2", 0], ["sp_skill_1", 0], ["sp_skill_2", 0], ["sp_skill_3", 0], ["sp_skill_4", 0], ["sp_skill_5", 0], ["sp_skill_evolution_1", 0], ["sp_skill_evolution_2", 0], ["sp_union_burst", 0], ["union_burst", 1272001], ["union_burst_evolution", 0], ["unit_id", 127201]],
            "new": [["ex_skill_1", 1272501], ["ex_skill_2", 0], ["ex_skill_3", 0], ["ex_skill_4", 0], ["ex_skill_5", 0], ["ex_skill_evolution_1", 1272511], ["ex_skill_evolution_2", 0], ["ex_skill_evolution_3", 0], ["ex_skill_evolution_4", 0], ["ex_skill_evolution_5", 0], ["main_skill_1", 1272002], ["main_skill_10", 0], ["main_skill_2", 1272003], ["main_skill_3", 0], ["main_skill_4", 0], ["main_skill_5", 0], ["main_skill_6", 0], ["main_skill_7", 0], ["main_skill_8", 0], ["main_skill_9", 0], ["main_skill_evolution_1", 1272012], ["main_skill_evolution_2", 0], ["sp_skill_1", 0], ["sp_skill_2", 0], ["sp_skill_3", 0], ["sp_skill_4", 0], ["sp_skill_5", 0], ["sp_skill_evolution_1", 0], ["sp_skill_evolution_2", 0], ["sp_union_burst", 0], ["union_burst", 1272001], ["union_burst_evolution", 0], ["unit_id", 127201]]
          }
        ]
      }
    },
    "tower_schedule": {
      "data_changes": {
        "modified": [
          {
            "id": 1054,
            "old": [["count_start_time", "2025/01/14 15:59:59"], ["end_time", "2025/01/15 15:59:59"], ["max_tower_area_id", 54], ["opening_story_id", 7028003], ["recovery_disable_time", "2025/01/15 00:00:00"], ["start_time", "2025/01/10 16:00:00"], ["tower_schedule_id", 1054]],
            "new": [["count_start_time", "2025/02/14 15:59:59"], ["end_time", "2025/02/15 15:59:59"], ["max_tower_area_id", 54], ["opening_story_id", 7028003], ["recovery_disable_time", "2025/02/15 00:00:00"], ["start_time", "2025/02/10 16:00:00"], ["tower_schedule_id", 1054]]
          }
        ]
      }
    },
    "chara_story_status": {
      "data_changes": {
        "added": [
          [["chara_id_1", 1277], ["chara_id_10", 0], ["chara_id_11", 0], ["chara_id_12", 0], ["chara_id_13", 0], ["chara_id_14", 0], ["chara_id_15", 0], ["chara_id_16", 0], ["chara_id_17", 0], ["chara_id_18", 0], ["chara_id_19", 0], ["chara_id_2", 0], ["chara_id_20", 0], ["chara_id_3", 0], ["chara_id_4", 0], ["chara_id_5", 0], ["chara_id_6", 0], ["chara_id_7", 0], ["chara_id_8", 0], ["chara_id_9", 0], ["status_rate_1", 30], ["status_rate_2", 0], ["status_rate_3", 0], ["status_rate_4", 0], ["status_rate_5", 0], ["status_type_1", 4], ["status_type_2", 0], ["status_type_3", 0], ["status_type_4", 0], ["status_type_5", 0], ["story_id", 1277003], ["unlock_story_name", "琳德のエピソード第3話"]],
          [["chara_id_1", 1277], ["chara_id_10", 0], ["chara_id_11", 0], ["chara_id_12", 0], ["chara_id_13", 0], ["chara_id_14", 0], ["chara_id_15", 0], ["chara_id_16", 0], ["chara_id_17", 0], ["chara_id_18", 0], ["chara_id_19", 0], ["chara_id_2", 0], ["chara_id_20", 0], ["chara_id_3", 0], ["chara_id_4", 0], ["chara_id_5", 0], ["chara_id_6", 0], ["chara_id_7", 0], ["chara_id_8", 0], ["chara_id_9", 0], ["status_rate_1", 10], ["status_rate_2", 0], ["status_rate_3", 0], ["status_rate_4", 0], ["status_rate_5", 0], ["status_type_1", 4], ["status_type_2", 0], ["status_type_3", 0], ["status_type_4", 0], ["status_type_5", 0], ["story_id", 1277002], ["unlock_story_name", "琳德のエピソード第2話"]],
          [["chara_id_1", 1277], ["chara_id_10", 0], ["chara_id_11", 0], ["chara_id_12", 0], ["chara_id_13", 0], ["chara_id_14", 0], ["chara_id_15", 0], ["chara_id_16", 0], ["chara_id_17", 0], ["chara_id_18", 0], ["chara_id_19", 0], ["chara_id_2", 0], ["chara_id_20", 0], ["chara_id_3", 0], ["chara_id_4", 0], ["chara_id_5", 0], ["chara_id_6", 0], ["chara_id_7", 0], ["chara_id_8", 0], ["chara_id_9", 0], ["status_rate_1", 50], ["status_rate_2", 0], ["status_rate_3", 0], ["status_rate_4", 0], ["status_rate_5", 0], ["status_type_1", 4], ["status_type_2", 0], ["status_type_3", 0], ["status_type_4", 0], ["status_type_5", 0], ["story_id", 1277004], ["unlock_story_name", "琳德のエピソード第4話"]]
        ]
      }
    },
    "album_production_list": {
      "data_changes": {
        "added": [
          [["description", ""], ["id", 12770108], ["title", "羈絆Rank表演7"], ["type", 107], ["unit_id", 127701]],
          [["description", ""], ["id", 12770103], ["title", "羈絆Rank表演2"], ["type", 102], ["unit_id", 127701]],
          [["description", ""], ["id", 12770101], ["title", "解放表演1"], ["type", 201], ["unit_id", 127701]],
          [["description", ""], ["id", 12770102], ["title", "羈絆Rank表演1"], ["type", 101], ["unit_id", 127701]],
          [["description", ""], ["id", 12770105], ["title", "羈絆Rank表演4"], ["type", 104], ["unit_id", 127701]],
          [["description", ""], ["id", 12770104], ["title", "羈絆Rank表演3"], ["type", 103], ["unit_id", 127701]],
          [["description", ""], ["id", 12770106], ["title", "羈絆Rank表演5"], ["type", 105], ["unit_id", 127701]],
          [["description", ""], ["id", 12770107], ["title", "羈絆Rank表演6"], ["type", 106], ["unit_id", 127701]]
        ]
      }
    },
    "gacha_data": {
      "data_changes": {
        "added": [
          [["b445862d0ab66dcf0d21148e77310f8e2f88e53c87861cd1b30c6271489741b7", 0], ["chara_odds_star1", "30349_1"], ["chara_odds_star2", "30349_2"], ["chara_odds_star3", "30349_3"], ["description", "限定角色復刻！登場機率在期間內提升！\\n『10 連轉蛋』確定有1個5等以上！"], ["description_2", ""], ["description_sp", ""], ["discount_price", 50], ["end_time", "2025/02/13 15:59:59"], ["exchange_id", 349], ["ff12a2d323be4140b5b5f0e3db8f93c207d4d0594eff84913f280ebb8f5fbfcd", 0], ["free_gacha_count", 0], ["free_gacha_interval_time", 0], ["free_gacha_type", 0], ["gacha10_special_odds_star1", "0"], ["gacha10_special_odds_star2", "0"], ["gacha10_special_odds_star3", "0"], ["gacha_bonus_id", 0], ["gacha_cost_type", 2], ["gacha_detail", 2], ["gacha_id", 30349], ["gacha_name", "獎勵轉蛋"], ["gacha_odds", "0"], ["gacha_odds_star2", "0"], ["gacha_times_limit10", 0], ["gacha_type", 1], ["movie_id", 300349], ["parallel_id", 0], ["pick_up_chara_text", "凱留（插班生）"], ["pickup_badge", 0], ["pickup_id", 0], ["price", 150], ["prizegacha_id", 100147], ["rarity_odds", "300000"], ["special_id", 0], ["start_time", "2025/02/10 16:00:00"], ["tab_name", ""], ["ticket_id", 24001], ["ticket_id_10", 24004], ["title_id", 0]],
          [["b445862d0ab66dcf0d21148e77310f8e2f88e53c87861cd1b30c6271489741b7", 0], ["chara_odds_star1", "0"], ["chara_odds_star2", "0"], ["chara_odds_star3", "0"], ["description", "取得道具獎勵或記憶碎片吧！"], ["description_2", ""], ["description_sp", ""], ["discount_price", 0], ["end_time", "2025/02/17 15:59:59"], ["exchange_id", 0], ["ff12a2d323be4140b5b5f0e3db8f93c207d4d0594eff84913f280ebb8f5fbfcd", 0], ["free_gacha_count", 10], ["free_gacha_interval_time", 0], ["free_gacha_type", 1], ["gacha10_special_odds_star1", "0"], ["gacha10_special_odds_star2", "0"], ["gacha10_special_odds_star3", "0"], ["gacha_bonus_id", 0], ["gacha_cost_type", 3], ["gacha_detail", 1], ["gacha_id", 10349], ["gacha_name", "一般轉蛋"], ["gacha_odds", "10349"], ["gacha_odds_star2", ""], ["gacha_times_limit10", 0], ["gacha_type", 0], ["movie_id", 0], ["parallel_id", 0], ["pick_up_chara_text", ""], ["pickup_badge", 0], ["pickup_id", 0], ["price", 0], ["prizegacha_id", 0], ["rarity_odds", "0"], ["special_id", 0], ["start_time", "2025/02/10 16:00:00"], ["tab_name", ""], ["ticket_id", 0], ["ticket_id_10", 0], ["title_id", 0]],
          [["b445862d0ab66dcf0d21148e77310f8e2f88e53c87861cd1b30c6271489741b7", 0], ["chara_odds_star1", "30350_1"], ["chara_odds_star2", "30350_2"], ["chara_odds_star3", "30350_3"], ["description", "新角色「琳德」登場！\\n期間內登場機率UP！"], ["description_2", "[3C404E]每次讓目標角色加入時[FFBB00,CE4F00][-]獲得[-]角色記憶碎片200個！"], ["description_sp", ""], ["discount_price", 50], ["end_time", "2025/02/17 15:59:59"], ["exchange_id", 350], ["ff12a2d323be4140b5b5f0e3db8f93c207d4d0594eff84913f280ebb8f5fbfcd", 0], ["free_gacha_count", 0], ["free_gacha_interval_time", 0], ["free_gacha_type", 0], ["gacha10_special_odds_star1", "0"], ["gacha10_special_odds_star2", "0"], ["gacha10_special_odds_star3", "0"], ["gacha_bonus_id", 1155], ["gacha_cost_type", 2], ["gacha_detail", 2], ["gacha_id", 30350], ["gacha_name", "精選轉蛋"], ["gacha_odds", "0"], ["gacha_odds_star2", "0"], ["gacha_times_limit10", 1], ["gacha_type", 1], ["movie_id", 300350], ["parallel_id", 0], ["pick_up_chara_text", "琳德"], ["pickup_badge", 0], ["pickup_id", 0], ["price", 150], ["prizegacha_id", 0], ["rarity_odds", "300000"], ["special_id", 0], ["start_time", "2025/02/10 16:00:00"], ["tab_name", ""], ["ticket_id", 24001], ["ticket_id_10", 24004], ["title_id", 0]],
          [["b445862d0ab66dcf0d21148e77310f8e2f88e53c87861cd1b30c6271489741b7", 2], ["chara_odds_star1", "70120_1"], ["chara_odds_star2", "70120_2"], ["chara_odds_star3", "70120_3"], ["description", "有償寶石限定\\n舉辦★3確定白金轉蛋！"], ["description_2", "[3C404E]第10位角色[FFBB00,CE4F00]必定出現★3角色！[-] 可以取得大師碎片×1！[-]"], ["description_sp", ""], ["discount_price", 50], ["end_time", "2025/02/17 15:59:59"], ["exchange_id", 350], ["ff12a2d323be4140b5b5f0e3db8f93c207d4d0594eff84913f280ebb8f5fbfcd", 1], ["free_gacha_count", 0], ["free_gacha_interval_time", 0], ["free_gacha_type", 0], ["gacha10_special_odds_star1", "0"], ["gacha10_special_odds_star2", "0"], ["gacha10_special_odds_star3", "0"], ["gacha_bonus_id", 1155], ["gacha_cost_type", 2], ["gacha_detail", 2], ["gacha_id", 70120], ["gacha_name", "★3確定白金轉蛋"], ["gacha_odds", "0"], ["gacha_odds_star2", "0"], ["gacha_times_limit10", 0], ["gacha_type", 1], ["movie_id", 700091], ["parallel_id", 0], ["pick_up_chara_text", "無精選角色"], ["pickup_badge", 0], ["pickup_id", 0], ["price", 1500], ["prizegacha_id", 0], ["rarity_odds", "300000"], ["special_id", 70119], ["start_time", "2025/02/13 16:00:00"], ["tab_name", ""], ["ticket_id", 24001], ["ticket_id_10", 0], ["title_id", 0]],
          [["b445862d0ab66dcf0d21148e77310f8e2f88e53c87861cd1b30c6271489741b7", 0], ["chara_odds_star1", "20349_1"], ["chara_odds_star2", "20349_2"], ["chara_odds_star3", "20349_3"], ["description", "白金轉蛋僅會出現角色喔！"], ["description_2", ""], ["description_sp", ""], ["discount_price", 50], ["end_time", "2025/02/17 15:59:59"], ["exchange_id", 350], ["ff12a2d323be4140b5b5f0e3db8f93c207d4d0594eff84913f280ebb8f5fbfcd", 0], ["free_gacha_count", 0], ["free_gacha_interval_time", 0], ["free_gacha_type", 0], ["gacha10_special_odds_star1", "0"], ["gacha10_special_odds_star2", "0"], ["gacha10_special_odds_star3", "0"], ["gacha_bonus_id", 0], ["gacha_cost_type", 2], ["gacha_detail", 2], ["gacha_id", 20349], ["gacha_name", "白金轉蛋"], ["gacha_odds", "0"], ["gacha_odds_star2", "0"], ["gacha_times_limit10", 0], ["gacha_type", 1], ["movie_id", 200001], ["parallel_id", 0], ["pick_up_chara_text", "無精選角色"], ["pickup_badge", 0], ["pickup_id", 0], ["price", 150], ["prizegacha_id", 0], ["rarity_odds", "300000"], ["special_id", 0], ["start_time", "2025/02/10 16:00:00"], ["tab_name", ""], ["ticket_id", 24001], ["ticket_id_10", 24004], ["title_id", 0]],
          [["b445862d0ab66dcf0d21148e77310f8e2f88e53c87861cd1b30c6271489741b7", 2], ["chara_odds_star1", "70119_1"], ["chara_odds_star2", "70119_2"], ["chara_odds_star3", "70119_3"], ["description", "有償寶石限定\\n舉辦★3確定白金轉蛋！"], ["description_2", "[3C404E]第10位角色[FFBB00,CE4F00]必定出現★3角色！[-] 可以取得大師碎片×1！[-]"], ["description_sp", ""], ["discount_price", 50], ["end_time", "2025/02/13 15:59:59"], ["exchange_id", 350], ["ff12a2d323be4140b5b5f0e3db8f93c207d4d0594eff84913f280ebb8f5fbfcd", 1], ["free_gacha_count", 0], ["free_gacha_interval_time", 0], ["free_gacha_type", 0], ["gacha10_special_odds_star1", "0"], ["gacha10_special_odds_star2", "0"], ["gacha10_special_odds_star3", "0"], ["gacha_bonus_id", 1155], ["gacha_cost_type", 2], ["gacha_detail", 2], ["gacha_id", 70119], ["gacha_name", "★3確定白金轉蛋"], ["gacha_odds", "0"], ["gacha_odds_star2", "0"], ["gacha_times_limit10", 0], ["gacha_type", 1], ["movie_id", 700091], ["parallel_id", 0], ["pick_up_chara_text", "無精選角色"], ["pickup_badge", 0], ["pickup_id", 0], ["price", 1500], ["prizegacha_id", 0], ["rarity_odds", "300000"], ["special_id", 70119], ["start_time", "2025/02/10 16:00:00"], ["tab_name", ""], ["ticket_id", 24001], ["ticket_id_10", 0], ["title_id", 0]]
        ]
      }
    },
    "ub_auto_define": {
      "data_changes": {
        "added": [
          [["skill_id", 1277001], ["ub_auto_id_1", 1], ["ub_auto_id_2", 0], ["ub_auto_id_3", 0], ["ub_auto_id_4", 0], ["ub_auto_id_5", 0]]
        ]
      }
    },
    "unique_equip_enhance_rate": {
      "data_changes": {
        "added": [
          [["accuracy", 0.0], ["atk", 0.0], ["def", 0.0], ["dodge", 0.0], ["energy_recovery_rate", 0.1], ["energy_reduce_rate", 0.0], ["equipment_id", 132721], ["hp", 12.0], ["hp_recovery_rate", 0.0], ["id", 1327210], ["life_steal", 0.0], ["magic_critical", 0.0], ["magic_def", 0.0], ["magic_penetrate", 0.0], ["magic_str", 3.0], ["max_lv", 260], ["min_lv", 2], ["physical_critical", 0.0], ["physical_penetrate", 0.0], ["wave_energy_recovery", 0.0], ["wave_hp_recovery", 0.0]],
          [["accuracy", 0.0], ["atk", 4.25], ["def", 0.0], ["dodge", 0.0], ["energy_recovery_rate", 0.0], ["energy_reduce_rate", 0.0], ["equipment_id", 132731], ["hp", 0.0], ["hp_recovery_rate", 0.0], ["id", 1327310], ["life_steal", 0.0], ["magic_critical", 0.0], ["magic_def", 0.0], ["magic_penetrate", 0.0], ["magic_str", 0.0], ["max_lv", -1], ["min_lv", 2], ["physical_critical", 1.25], ["physical_penetrate", 0.0], ["wave_energy_recovery", 0.0], ["wave_hp_recovery", 0.0]],
          [["accuracy", 0.0], ["atk", 0.0], ["def", 0.0], ["dodge", 0.0], ["energy_recovery_rate", 0.0], ["energy_reduce_rate", 0.0], ["equipment_id", 132721], ["hp", 12.0], ["hp_recovery_rate", 0.0], ["id", 1327211], ["life_steal", 0.0], ["magic_critical", 0.0], ["magic_def", 0.0], ["magic_penetrate", 0.0], ["magic_str", 3.5], ["max_lv", -1], ["min_lv", 261], ["physical_critical", 0.0], ["physical_penetrate", 0.0], ["wave_energy_recovery", 0.0], ["wave_hp_recovery", 0.0]]
        ]
      }
    },
    "skill_data": {
      "data_changes": {
        "added": [
          [["action_1", 127301201], ["action_10", 0], ["action_2", 127301202], ["action_3", 127301203], ["action_4", 127301204], ["action_5", 127301205], ["action_6", 0], ["action_7", 0], ["action_8", 0], ["action_9", 0], ["boss_ub_cool_time", 0.0], ["depend_action_1", 0], ["depend_action_10", 0], ["depend_action_2", 0], ["depend_action_3", 0], ["depend_action_4", 127301203], ["depend_action_5", 0], ["depend_action_6", 0], ["depend_action_7", 0], ["depend_action_8", 0], ["depend_action_9", 0], ["description", "對面前的１名敵人造成大幅度的物理傷害，並中幅度恢復自身的ＴＰ。當此技能暴擊時，特大幅度提升自身周圍的我方全體的物理攻擊力，大幅度提升物理暴擊率。"], ["icon_type", 2001], ["name", "青春全景+"], ["skill_area_width", 0], ["skill_cast_time", 1.05], ["skill_id", 1273012], ["skill_type", 0]],
          [["action_1", 127751101], ["action_10", 0], ["action_2", 0], ["action_3", 0], ["action_4", 0], ["action_5", 0], ["action_6", 0], ["action_7", 0], ["action_8", 0], ["action_9", 0], ["boss_ub_cool_time", 0.0], ["depend_action_1", 0], ["depend_action_10", 0], ["depend_action_2", 0], ["depend_action_3", 0], ["depend_action_4", 0], ["depend_action_5", 0], ["depend_action_6", 0], ["depend_action_7", 0], ["depend_action_8", 0], ["depend_action_9", 0], ["description", "戰鬥開始時，大幅度提升自己的魔法防禦力。"], ["icon_type", 3004], ["name", "洗衣大師+"], ["skill_area_width", 0], ["skill_cast_time", 0.0], ["skill_id", 1277511], ["skill_type", 0]],
          [["action_1", 127700201], ["action_10", 0], ["action_2", 127700202], ["action_3", 127700203], ["action_4", 127700204], ["action_5", 127700205], ["action_6", 127700206], ["action_7", 127700207], ["action_8", 0], ["action_9", 0], ["boss_ub_cool_time", 0.0], ["depend_action_1", 0], ["depend_action_10", 0], ["depend_action_2", 0], ["depend_action_3", 127700202], ["depend_action_4", 127700202], ["depend_action_5", 0], ["depend_action_6", 127700205], ["depend_action_7", 127700205], ["depend_action_8", 0], ["depend_action_9", 0], ["description", "以自身為中心，中幅度提升範圍內我方全體的魔法攻擊力和魔法暴擊率，並小幅度提升魔法攻擊暴擊時的傷害。【領域展開時】，將會再次發動此技能的效果。"], ["icon_type", 2003], ["name", "我要打掃！"], ["skill_area_width", 0], ["skill_cast_time", 1.05], ["skill_id", 1277002], ["skill_type", 1]],
          [["action_1", 127750101], ["action_10", 0], ["action_2", 0], ["action_3", 0], ["action_4", 0], ["action_5", 0], ["action_6", 0], ["action_7", 0], ["action_8", 0], ["action_9", 0], ["boss_ub_cool_time", 0.0], ["depend_action_1", 0], ["depend_action_10", 0], ["depend_action_2", 0], ["depend_action_3", 0], ["depend_action_4", 0], ["depend_action_5", 0], ["depend_action_6", 0], ["depend_action_7", 0], ["depend_action_8", 0], ["depend_action_9", 0], ["description", "戰鬥開始時，中幅度提升自己的魔法防禦力。"], ["icon_type", 3004], ["name", "洗衣大師"], ["skill_area_width", 0], ["skill_cast_time", 0.0], ["skill_id", 1277501], ["skill_type", 0]],
          [["action_1", 127700101], ["action_10", 0], ["action_2", 127700102], ["action_3", 127700103], ["action_4", 127700104], ["action_5", 127700105], ["action_6", 0], ["action_7", 0], ["action_8", 0], ["action_9", 0], ["boss_ub_cool_time", 0.0], ["depend_action_1", 0], ["depend_action_10", 0], ["depend_action_2", 0], ["depend_action_3", 0], ["depend_action_4", 0], ["depend_action_5", 0], ["depend_action_6", 0], ["depend_action_7", 0], ["depend_action_8", 0], ["depend_action_9", 0], ["description", "以自身為中心，特大幅度提升範圍內我方全體的魔法攻擊力，大幅度提升魔法暴擊率，小幅度提升魔法攻擊暴擊時的傷害。同時中幅度恢復ＨＰ，並展開可小幅度恢復範圍內我方全體ＨＰ的領域。"], ["icon_type", 1003], ["name", "真摯服務"], ["skill_area_width", 0], ["skill_cast_time", 0.0], ["skill_id", 1277001], ["skill_type", 1]],
          [["action_1", 127201201], ["action_10", 0], ["action_2", 127201202], ["action_3", 127201203], ["action_4", 0], ["action_5", 0], ["action_6", 0], ["action_7", 0], ["action_8", 0], ["action_9", 0], ["boss_ub_cool_time", 0.0], ["depend_action_1", 0], ["depend_action_10", 0], ["depend_action_2", 0], ["depend_action_3", 0], ["depend_action_4", 0], ["depend_action_5", 0], ["depend_action_6", 0], ["depend_action_7", 0], ["depend_action_8", 0], ["depend_action_9", 0], ["description", "特大幅度提升所有進行魔法攻擊的我方角色的魔法攻擊力，大幅度提升魔法暴擊率，大幅度提升行動速度。"], ["icon_type", 2003], ["name", "強化之書+"], ["skill_area_width", 0], ["skill_cast_time", 0.59], ["skill_id", 1272012], ["skill_type", 0]],
          [["action_1", 127700301], ["action_10", 0], ["action_2", 127700302], ["action_3", 127700303], ["action_4", 127700304], ["action_5", 127700305], ["action_6", 127700306], ["action_7", 127700307], ["action_8", 127700308], ["action_9", 127700309], ["boss_ub_cool_time", 0.0], ["depend_action_1", 0], ["depend_action_10", 0], ["depend_action_2", 0], ["depend_action_3", 127700302], ["depend_action_4", 127700302], ["depend_action_5", 127700302], ["depend_action_6", 0], ["depend_action_7", 127700306], ["depend_action_8", 127700306], ["depend_action_9", 127700306], ["description", "以自身為中心，中幅度提升範圍內我方全體的魔法攻擊力和魔法防禦力，同時展開魔法無效的護盾。此外，小幅度恢復ＴＰ。【領域展開時】，將會再次發動此技能的效果。"], ["icon_type", 2013], ["name", "送慰勞品來囉♪"], ["skill_area_width", 0], ["skill_cast_time", 1.05], ["skill_id", 1277003], ["skill_type", 1]]
        ]
      }
    },
    "emblem_mission_reward_data": {
      "data_changes": {
        "added": [
          [["icon_type", 1003], ["id", 1445], ["mission_reward_id", 56011907], ["reward_id", 10201907], ["reward_num", 1], ["reward_type", 15]],
          [["icon_type", 1001], ["id", 1443], ["mission_reward_id", 56011905], ["reward_id", 10201905], ["reward_num", 1], ["reward_type", 15]],
          [["icon_type", 0], ["id", 1446], ["mission_reward_id", 56011907], ["reward_id", 91002], ["reward_num", 50], ["reward_type", 8]],
          [["icon_type", 1002], ["id", 1444], ["mission_reward_id", 56011906], ["reward_id", 10201906], ["reward_num", 1], ["reward_type", 15]]
        ]
      }
    },
    "exceed_level_unit": {
      "data_changes": {
        "added": [
          [["consume_num_1", 120], ["consume_num_2", 20000000], ["consume_num_3", 0], ["consume_num_4", 0], ["consume_num_5", 0], ["exceed_item_id", 41277], ["exceed_stage", 1], ["id", 1127701], ["item_id_1", 31277], ["item_id_2", 94000], ["item_id_3", 0], ["item_id_4", 0], ["item_id_5", 0], ["reward_type_1", 2], ["reward_type_2", 12], ["reward_type_3", 0], ["reward_type_4", 0], ["reward_type_5", 0], ["unit_id", 127701]]
        ]
      }
    },
    "unlock_rarity_6": {
      "data_changes": {
        "added": [
          [["accuracy", 0], ["atk", 0], ["consume_gold", 0], ["def", 0], ["dodge", 0], ["energy_recovery_rate", 0], ["energy_reduce_rate", 0], ["hp", 0], ["hp_recovery_rate", 0], ["life_steal", 0], ["magic_critical", 0], ["magic_def", 0], ["magic_penetrate", 0], ["magic_str", 0], ["material_count", 0], ["material_id", 0], ["material_type", 0], ["physical_critical", 0], ["physical_penetrate", 0], ["slot_id", 1], ["unit_id", 127701], ["unlock_flag", 0], ["unlock_level", 0], ["wave_energy_recovery", 0], ["wave_hp_recovery", 0]]
        ]
      }
    },
    "unit_ex_equipment_slot": {
      "data_changes": {
        "added": [
          [["slot_category_1", 110], ["slot_category_2", 203], ["slot_category_3", 305], ["unit_id", 127701]]
        ]
      }
    },
    "actual_unit_background": {
      "data_changes": {
        "added": [
          [["bg_id", 510350], ["face_type", 2], ["unit_id", 127731], ["unit_name", "燐人"]]
        ]
      }
    },
    "unit_promotion": {
      "data_changes": {
        "added": [
          [["equip_slot_1", 109254], ["equip_slot_2", 109253], ["equip_slot_3", 109373], ["equip_slot_4", 109372], ["equip_slot_5", 109613], ["equip_slot_6", 109582], ["promotion_level", 30], ["unit_id", 127701]]
        ]
      }
    },
    "unit_background": {
      "data_changes": {
        "added": [
          [["bg_id", 501730], ["bg_name", "吉歐‧提格尼亞_芭菲之城_大廳"], ["face_type", 20], ["position", 0.0], ["unit_id", 127701], ["unit_name", "琳德"]]
        ]
      }
    },
    "still": {
      "data_changes": {
        "added": [
          [["album_ignore", 0], ["facial_id", 1], ["my_page_flag", 1], ["position_y", 0], ["scroll_direction", 0], ["still_group_id", 1277004], ["still_id", 127700402], ["story_group_id", 1277], ["story_id", 1277004], ["unit_id_1", 127731], ["unit_id_10", 0], ["unit_id_2", 0], ["unit_id_3", 0], ["unit_id_4", 0], ["unit_id_5", 0], ["unit_id_6", 0], ["unit_id_7", 0], ["unit_id_8", 0], ["unit_id_9", 0], ["vertical_still_flg", 0]],
          [["album_ignore", 0], ["facial_id", 1], ["my_page_flag", 1], ["position_y", 0], ["scroll_direction", 0], ["still_group_id", 1277004], ["still_id", 127700406], ["story_group_id", 1277], ["story_id", 1277004], ["unit_id_1", 127731], ["unit_id_10", 0], ["unit_id_2", 0], ["unit_id_3", 0], ["unit_id_4", 0], ["unit_id_5", 0], ["unit_id_6", 0], ["unit_id_7", 0], ["unit_id_8", 0], ["unit_id_9", 0], ["vertical_still_flg", 0]],
          [["album_ignore", 0], ["facial_id", 1], ["my_page_flag", 1], ["position_y", 0], ["scroll_direction", 0], ["still_group_id", 1277004], ["still_id", 127700401], ["story_group_id", 1277], ["story_id", 1277004], ["unit_id_1", 127731], ["unit_id_10", 0], ["unit_id_2", 0], ["unit_id_3", 0], ["unit_id_4", 0], ["unit_id_5", 0], ["unit_id_6", 0], ["unit_id_7", 0], ["unit_id_8", 0], ["unit_id_9", 0], ["vertical_still_flg", 0]],
          [["album_ignore", 0], ["facial_id", 1], ["my_page_flag", 1], ["position_y", 0], ["scroll_direction", 0], ["still_group_id", 1277003], ["still_id", 127700301], ["story_group_id", 1277], ["story_id", 1277003], ["unit_id_1", 127712], ["unit_id_10", 0], ["unit_id_2", 193511], ["unit_id_3", 0], ["unit_id_4", 0], ["unit_id_5", 0], ["unit_id_6", 0], ["unit_id_7", 0], ["unit_id_8", 0], ["unit_id_9", 0], ["vertical_still_flg", 0]],
          [["album_ignore", 0], ["facial_id", 1], ["my_page_flag", 1], ["position_y", 0], ["scroll_direction", 0], ["still_group_id", 1277004], ["still_id", 127700403], ["story_group_id", 1277], ["story_id", 1277004], ["unit_id_1", 127731], ["unit_id_10", 0], ["unit_id_2", 0], ["unit_id_3", 0], ["unit_id_4", 0], ["unit_id_5", 0], ["unit_id_6", 0], ["unit_id_7", 0], ["unit_id_8", 0], ["unit_id_9", 0], ["vertical_still_flg", 0]],
          [["album_ignore", 0], ["facial_id", 1], ["my_page_flag", 1], ["position_y", 0], ["scroll_direction", 0], ["still_group_id", 1277004], ["still_id", 127700405], ["story_group_id", 1277], ["story_id", 1277004], ["unit_id_1", 127731], ["unit_id_10", 0], ["unit_id_2", 0], ["unit_id_3", 0], ["unit_id_4", 0], ["unit_id_5", 0], ["unit_id_6", 0], ["unit_id_7", 0], ["unit_id_8", 0], ["unit_id_9", 0], ["vertical_still_flg", 0]],
          [["album_ignore", 0], ["facial_id", 1], ["my_page_flag", 1], ["position_y", 0], ["scroll_direction", 0], ["still_group_id", 1277004], ["still_id", 127700404], ["story_group_id", 1277], ["story_id", 1277004], ["unit_id_1", 127731], ["unit_id_10", 0], ["unit_id_2", 0], ["unit_id_3", 0], ["unit_id_4", 0], ["unit_id_5", 0], ["unit_id_6", 0], ["unit_id_7", 0], ["unit_id_8", 0], ["unit_id_9", 0], ["vertical_still_flg", 0]],
          [["album_ignore", 0], ["facial_id", 1], ["my_page_flag", 1], ["position_y", 0], ["scroll_direction", 0], ["still_group_id", 1277003], ["still_id", 127700302], ["story_group_id", 1277], ["story_id", 1277003], ["unit_id_1", 127712], ["unit_id_10", 0], ["unit_id_2", 193511], ["unit_id_3", 0], ["unit_id_4", 0], ["unit_id_5", 0], ["unit_id_6", 0], ["unit_id_7", 0], ["unit_id_8", 0], ["unit_id_9", 0], ["vertical_still_flg", 0]]
        ]
      }
    },
    "unit_profile": {
      "data_changes": {
        "added": [
          [["age", "12"], ["birth_day", "5"], ["birth_month", "2"], ["blood_type", "?"], ["catch_copy", "認真又拼命的龍女僕（姊）"], ["favorite", "與妹妹一起度過的假日"], ["guild", "？？？"], ["guild_id", ""], ["height", "145"], ["race", "龍人族"], ["self_text", ""], ["unit_id", 127701], ["unit_name", "琳德"], ["voice", "豐田萌繪"], ["voice_id", 0], ["weight", "???"]]
        ]
      }
    },
    "app_icon": {
      "data_changes": {
        "added": [
          [["id", 127731]]
        ]
      }
    },
    "unit_promotion_status": {
      "data_changes": {
        "added": [
          [["accuracy", 0.0], ["atk", 52.0], ["def", 543.0], ["dodge", 3.0], ["energy_recovery_rate", 20.0], ["energy_reduce_rate", 19.0], ["hp", 11455.0], ["hp_recovery_rate", 136.0], ["life_steal", 0.0], ["magic_critical", 317.0], ["magic_def", 743.0], ["magic_penetrate", 0.0], ["magic_str", 8758.0], ["physical_critical", 0.0], ["physical_penetrate", 0.0], ["promotion_level", 24], ["unit_id", 127701], ["wave_energy_recovery", 183.0], ["wave_hp_recovery", 1490.0]]
        ]
      }
    },
    "emblem_mission_data": {
      "data_changes": {
        "added": [
          [["category_icon", 301], ["condition_num", 3], ["condition_value_1", 127701], ["condition_value_2", 0], ["condition_value_3", 0], ["description", "將琳德升到★3"], ["disp_group", 201278], ["end_time", "2030/04/01 14:59:59"], ["mission_condition", 6011], ["mission_id", 56011906], ["mission_reward_id", 56011906], ["start_time", "2025/02/10 16:00:00"], ["system_id", 501], ["visible_flag", 1]],
          [["category_icon", 301], ["condition_num", 5], ["condition_value_1", 127701], ["condition_value_2", 0], ["condition_value_3", 0], ["description", "將琳德升到★5"], ["disp_group", 201278], ["end_time", "2030/04/01 14:59:59"], ["mission_condition", 6011], ["mission_id", 56011907], ["mission_reward_id", 56011907], ["start_time", "2025/02/10 16:00:00"], ["system_id", 501], ["visible_flag", 1]],
          [["category_icon", 301], ["condition_num", 1], ["condition_value_1", 127701], ["condition_value_2", 0], ["condition_value_3", 0], ["description", "讓琳德成為夥伴"], ["disp_group", 201278], ["end_time", "2030/04/01 14:59:59"], ["mission_condition", 6011], ["mission_id", 56011905], ["mission_reward_id", 56011905], ["start_time", "2025/02/10 16:00:00"], ["system_id", 501], ["visible_flag", 1]]
        ]
      }
    },
    "unit_motion_list": {
      "data_changes": {
        "added": [
          [["sp_motion", 1], ["unit_id", 127701]]
        ]
      }
    },
    "room_unit_comments": {
      "data_changes": {
        "added": [
          [["beloved_step", 1], ["description", "自己變成\\n受到款待的那一方，\\n果然有點\\n不自在呢……"], ["face_id", 1], ["id", 8562], ["insert_word_type", 0], ["time", 0], ["trigger", 1], ["unit_id", 127701], ["voice_id", 4]]
        ]
      }
    },
    "daily_mission_data": {
      "data_changes": {
        "modified": [
          {
            "id": 11101001,
            "old": [["category_icon", 208], ["condition_num", 1], ["condition_value_1", 0], ["condition_value_2", 0], ["condition_value_3", 0], ["daily_mission_id", 11101001], ["description", "挑戰1次露娜之塔的冒險"], ["disp_group", 14], ["end_time", "2025/01/15 15:59:59"], ["max_level", 0], ["min_level", 0], ["mission_condition", 1101], ["mission_reward_id", 11101001], ["start_time", "2025/01/10 16:00:00"], ["system_id", 108], ["title_color_id", 0], ["visible_flag", 1]],
            "new": [["category_icon", 208], ["condition_num", 1], ["condition_value_1", 0], ["condition_value_2", 0], ["condition_value_3", 0], ["daily_mission_id", 11101001], ["description", "挑戰1次露娜之塔的冒險"], ["disp_group", 14], ["end_time", "2025/02/15 15:59:59"], ["max_level", 0], ["min_level", 0], ["mission_condition", 1101], ["mission_reward_id", 11101001], ["start_time", "2025/02/10 16:00:00"], ["system_id", 108], ["title_color_id", 0], ["visible_flag", 1]]
          }
        ]
      }
    },
    "chara_identity": {
      "data_changes": {
        "added": [
          [["chara_type", 277], ["chara_type_2", 0], ["chara_type_3", 0], ["unit_id", 127701]]
        ]
      }
    },
    "unit_attack_pattern": {
      "data_changes": {
        "added": [
          [["atk_pattern_1", 1002], ["atk_pattern_10", 0], ["atk_pattern_11", 0], ["atk_pattern_12", 0], ["atk_pattern_13", 0], ["atk_pattern_14", 0], ["atk_pattern_15", 0], ["atk_pattern_16", 0], ["atk_pattern_17", 0], ["atk_pattern_18", 0], ["atk_pattern_19", 0], ["atk_pattern_2", 1], ["atk_pattern_20", 0], ["atk_pattern_3", 1001], ["atk_pattern_4", 1], ["atk_pattern_5", 1001], ["atk_pattern_6", 1], ["atk_pattern_7", 1002], ["atk_pattern_8", 1], ["atk_pattern_9", 1001], ["loop_end", 9], ["loop_start", 5], ["pattern_id", 12770101], ["unit_id", 127701]]
        ]
      }
    },
    "unique_equipment_rankup": {
      "data_changes": {
        "added": [
          [["consume_num_1", 5], ["consume_num_10", 0], ["consume_num_2", 10], ["consume_num_3", 0], ["consume_num_4", 0], ["consume_num_5", 0], ["consume_num_6", 0], ["consume_num_7", 0], ["consume_num_8", 0], ["consume_num_9", 0], ["crafted_cost", 1000000], ["equip_id", 132721], ["item_id_1", 31272], ["item_id_10", 0], ["item_id_2", 140001], ["item_id_3", 0], ["item_id_4", 0], ["item_id_5", 0], ["item_id_6", 0], ["item_id_7", 0], ["item_id_8", 0], ["item_id_9", 0], ["reward_type_1", 2], ["reward_type_10", 0], ["reward_type_2", 4], ["reward_type_3", 0], ["reward_type_4", 0], ["reward_type_5", 0], ["reward_type_6", 0], ["reward_type_7", 0], ["reward_type_8", 0], ["reward_type_9", 0], ["unique_equip_rank", 21], ["unit_level", 280]],
          [["consume_num_1", 10], ["consume_num_10", 0], ["consume_num_2", 10], ["consume_num_3", 0], ["consume_num_4", 0], ["consume_num_5", 0], ["consume_num_6", 0], ["consume_num_7", 0], ["consume_num_8", 0], ["consume_num_9", 0], ["crafted_cost", 500000], ["equip_id", 132731], ["item_id_1", 31273], ["item_id_10", 0], ["item_id_2", 140001], ["item_id_3", 0], ["item_id_4", 0], ["item_id_5", 0], ["item_id_6", 0], ["item_id_7", 0], ["item_id_8", 0], ["item_id_9", 0], ["reward_type_1", 2], ["reward_type_10", 0], ["reward_type_2", 4], ["reward_type_3", 0], ["reward_type_4", 0], ["reward_type_5", 0], ["reward_type_6", 0], ["reward_type_7", 0], ["reward_type_8", 0], ["reward_type_9", 0], ["unique_equip_rank", 5], ["unit_level", 110]]
        ]
      }
    },
    "unique_equipment_data": {
      "data_changes": {
        "added": [
          [["accuracy", 0.0], ["atk", 85.0], ["craft_flg", 1], ["def", 0.0], ["description", "在入學安布羅斯魔法學園時，\\n鈴奈使用的書包。\\n跟大家一起度過的青春的放學後的回憶，\\n會成為絕不褪色的羈絆的證明。"], ["dodge", 0.0], ["enable_donation", 0], ["energy_recovery_rate", 0.0], ["energy_reduce_rate", 0.0], ["equipment_enhance_point", 0], ["equipment_id", 132731], ["equipment_name", "青春學園書包"], ["hp", 0.0], ["hp_recovery_rate", 0.0], ["life_steal", 0.0], ["magic_critical", 0.0], ["magic_def", 0.0], ["magic_penetrate", 0.0], ["magic_str", 0.0], ["physical_critical", 25.0], ["physical_penetrate", 0.0], ["promotion_level", 98], ["require_level", 1], ["sale_price", 0], ["wave_energy_recovery", 0.0], ["wave_hp_recovery", 0.0]],
          [["accuracy", 0.0], ["atk", 0.0], ["craft_flg", 1], ["def", 0.0], ["description", "在入學安布羅斯魔法學園時，\\n凱留穿戴著的帽子跟眼鏡。\\n無法取代的青春歲月，\\n會成為在面對困難時的自信與力量。"], ["dodge", 0.0], ["enable_donation", 0], ["energy_recovery_rate", 2.0], ["energy_reduce_rate", 0.0], ["equipment_enhance_point", 0], ["equipment_id", 132721], ["equipment_name", "青春學園學士帽組"], ["hp", 240.0], ["hp_recovery_rate", 0.0], ["life_steal", 0.0], ["magic_critical", 0.0], ["magic_def", 0.0], ["magic_penetrate", 0.0], ["magic_str", 60.0], ["physical_critical", 0.0], ["physical_penetrate", 0.0], ["promotion_level", 98], ["require_level", 1], ["sale_price", 0], ["wave_energy_recovery", 0.0], ["wave_hp_recovery", 0.0]]
        ]
      }
    },
    "unit_comments": {
      "data_changes": {
        "added": [
          [["all_comments_flag", 0], ["change_face", 1], ["change_face_2", 0], ["change_face_3", 0], ["change_time", 0.0], ["change_time_2", 0.0], ["change_time_3", 0.0], ["description", "你幫我把衣服\\n晾到高處了？\\n……謝謝。\\n多虧有你，真是幫了我大忙！"], ["face_id", 1], ["face_id_2", 0], ["face_id_3", 0], ["id", 1277009], ["target_unit_id", 0], ["unit_id", 127731], ["use_type", 1], ["voice_id", 4]],
          [["all_comments_flag", 0], ["change_face", 3], ["change_face_2", 0], ["change_face_3", 0], ["change_time", 7.8], ["change_time_2", 0.0], ["change_time_3", 0.0], ["description", "「吉歐‧提格尼亞」的人們\\n平常都太悠哉了。\\n而且還有點隨便……\\n所以我得振作起來！"], ["face_id", 4], ["face_id_2", 0], ["face_id_3", 0], ["id", 1277002], ["target_unit_id", 0], ["unit_id", 127701], ["use_type", 1], ["voice_id", 2]],
          [["all_comments_flag", 0], ["change_face", 1], ["change_face_2", 0], ["change_face_3", 0], ["change_time", 0.0], ["change_time_2", 0.0], ["change_time_3", 0.0], ["description", "果然好溫柔又好厲害……\\n啊，這樣不行！\\n騎士先生再怎麼溫柔，\\n都不能依賴他的好意……"], ["face_id", 1], ["face_id_2", 0], ["face_id_3", 0], ["id", 1277010], ["target_unit_id", 0], ["unit_id", 127731], ["use_type", 1], ["voice_id", 5]],
          [["all_comments_flag", 0], ["change_face", 8], ["change_face_2", 0], ["change_face_3", 0], ["change_time", 6.4], ["change_time_2", 0.0], ["change_time_3", 0.0], ["description", "騎士先生真是多才多藝呢。\\n而且既溫柔又可靠……\\n呃，我在說什麼啊……！？\\n請忘記我剛剛說的話！"], ["face_id", 2], ["face_id_2", 0], ["face_id_3", 0], ["id", 1277004], ["target_unit_id", 0], ["unit_id", 127701], ["use_type", 1], ["voice_id", 4]],
          [["all_comments_flag", 0], ["change_face", 3], ["change_face_2", 0], ["change_face_3", 0], ["change_time", 4.7], ["change_time_2", 0.0], ["change_time_3", 0.0], ["description", "烏爾姆她啊，又說我\\n好說話到太天真了……\\n我比她更穩重，\\n所以沒這回事對吧？"], ["face_id", 4], ["face_id_2", 0], ["face_id_3", 0], ["id", 1277003], ["target_unit_id", 0], ["unit_id", 127701], ["use_type", 1], ["voice_id", 3]],
          [["all_comments_flag", 0], ["change_face", 3], ["change_face_2", 0], ["change_face_3", 0], ["change_time", 5.2], ["change_time_2", 0.0], ["change_time_3", 0.0], ["description", "萊拉耶爾殿下很溫柔，\\n總是心懷萬民。\\n作為那位大人的女僕，\\n我也想成為配得上這個身分的人。"], ["face_id", 2], ["face_id_2", 0], ["face_id_3", 0], ["id", 1277001], ["target_unit_id", 0], ["unit_id", 127701], ["use_type", 1], ["voice_id", 1]],
          [["all_comments_flag", 0], ["change_face", 5], ["change_face_2", 0], ["change_face_3", 0], ["change_time", 9.3], ["change_time_2", 0.0], ["change_time_3", 0.0], ["description", "祝你生日快樂！\\n萊拉耶爾殿下有提議，\\n要不要侍奉你一日作為慶祝……\\n您覺得如何，主人……？"], ["face_id", 2], ["face_id_2", 0], ["face_id_3", 0], ["id", 1277011], ["target_unit_id", 0], ["unit_id", 127701], ["use_type", 2], ["voice_id", 6]],
          [["all_comments_flag", 0], ["change_face", 2], ["change_face_2", 0], ["change_face_3", 0], ["change_time", 9.5], ["change_time_2", 0.0], ["change_time_3", 0.0], ["description", "如果能像騎士先生這樣\\n善解人意什麼都能做到，\\n我也能幫上大家更多忙吧？\\n然後總有一天也要報恩……！"], ["face_id", 6], ["face_id_2", 0], ["face_id_3", 0], ["id", 1277005], ["target_unit_id", 0], ["unit_id", 127701], ["use_type", 1], ["voice_id", 5]],
          [["all_comments_flag", 0], ["change_face", 1], ["change_face_2", 0], ["change_face_3", 0], ["change_time", 0.0], ["change_time_2", 0.0], ["change_time_3", 0.0], ["description", "等等要打掃房間、\\n上菜，然後……\\n今天一整天也要認真勤勞地\\n好好工作！好……！"], ["face_id", 1], ["face_id_2", 0], ["face_id_3", 0], ["id", 1277007], ["target_unit_id", 0], ["unit_id", 127731], ["use_type", 1], ["voice_id", 2]],
          [["all_comments_flag", 0], ["change_face", 1], ["change_face_2", 0], ["change_face_3", 0], ["change_time", 0.0], ["change_time_2", 0.0], ["change_time_3", 0.0], ["description", "天氣真好……\\n非常適合洗衣服呢。\\n這樣一來，就能把城裡所有人的\\n床單都洗得鬆鬆軟軟的了"], ["face_id", 1], ["face_id_2", 0], ["face_id_3", 0], ["id", 1277006], ["target_unit_id", 0], ["unit_id", 127731], ["use_type", 1], ["voice_id", 1]],
          [["all_comments_flag", 0], ["change_face", 1], ["change_face_2", 0], ["change_face_3", 0], ["change_time", 0.0], ["change_time_2", 0.0], ["change_time_3", 0.0], ["description", "哇，好漂亮的肥皂泡泡……♪\\n但為什麼會這麼多……\\n啊，烏爾姆！\\n別再偷懶了，快晾衣服！"], ["face_id", 1], ["face_id_2", 0], ["face_id_3", 0], ["id", 1277008], ["target_unit_id", 0], ["unit_id", 127731], ["use_type", 1], ["voice_id", 3]],
          [["all_comments_flag", 0], ["change_face", 1], ["change_face_2", 0], ["change_face_3", 0], ["change_time", 0.0], ["change_time_2", 0.0], ["change_time_3", 0.0], ["description", "因為騎士先生\\n也幫了我很多……所以……\\n作為慶祝，如果是我能做到的事，\\n無論什麼都請儘管說喔！"], ["face_id", 1], ["face_id_2", 0], ["face_id_3", 0], ["id", 1277012], ["target_unit_id", 0], ["unit_id", 127731], ["use_type", 2], ["voice_id", 6]]
        ]
      }
    },
    "unique_equipment_craft": {
      "data_changes": {
        "added": [
          [["consume_num_1", 50], ["consume_num_10", 0], ["consume_num_2", 3], ["consume_num_3", 0], ["consume_num_4", 0], ["consume_num_5", 0], ["consume_num_6", 0], ["consume_num_7", 0], ["consume_num_8", 0], ["consume_num_9", 0], ["crafted_cost", 1000000], ["equip_id", 132731], ["item_id_1", 31273], ["item_id_10", 0], ["item_id_2", 140000], ["item_id_3", 0], ["item_id_4", 0], ["item_id_5", 0], ["item_id_6", 0], ["item_id_7", 0], ["item_id_8", 0], ["item_id_9", 0], ["reward_type_1", 2], ["reward_type_10", 0], ["reward_type_2", 4], ["reward_type_3", 0], ["reward_type_4", 0], ["reward_type_5", 0], ["reward_type_6", 0], ["reward_type_7", 0], ["reward_type_8", 0], ["reward_type_9", 0]],
          [["consume_num_1", 50], ["consume_num_10", 0], ["consume_num_2", 3], ["consume_num_3", 0], ["consume_num_4", 0], ["consume_num_5", 0], ["consume_num_6", 0], ["consume_num_7", 0], ["consume_num_8", 0], ["consume_num_9", 0], ["crafted_cost", 1000000], ["equip_id", 132721], ["item_id_1", 31272], ["item_id_10", 0], ["item_id_2", 140000], ["item_id_3", 0], ["item_id_4", 0], ["item_id_5", 0], ["item_id_6", 0], ["item_id_7", 0], ["item_id_8", 0], ["item_id_9", 0], ["reward_type_1", 2], ["reward_type_10", 0], ["reward_type_2", 4], ["reward_type_3", 0], ["reward_type_4", 0], ["reward_type_5", 0], ["reward_type_6", 0], ["reward_type_7", 0], ["reward_type_8", 0], ["reward_type_9", 0]]
        ]
      }
    },
    "prizegacha_data": {
      "data_changes": {
        "added": [
          [["disp_prize_fixed_compensation", 5], ["gacha_prize1", 1], ["gacha_prize10", 10], ["prize_fixed_compensation", 5], ["prize_fixed_compensation_quantity", 1], ["prize_memory_id_1", 31272], ["prize_memory_id_10", 0], ["prize_memory_id_11", 0], ["prize_memory_id_12", 0], ["prize_memory_id_13", 0], ["prize_memory_id_14", 0], ["prize_memory_id_15", 0], ["prize_memory_id_16", 0], ["prize_memory_id_17", 0], ["prize_memory_id_18", 0], ["prize_memory_id_19", 0], ["prize_memory_id_2", 0], ["prize_memory_id_20", 0], ["prize_memory_id_21", 0], ["prize_memory_id_22", 0], ["prize_memory_id_23", 0], ["prize_memory_id_24", 0], ["prize_memory_id_25", 0], ["prize_memory_id_26", 0], ["prize_memory_id_27", 0], ["prize_memory_id_28", 0], ["prize_memory_id_29", 0], ["prize_memory_id_3", 0], ["prize_memory_id_30", 0], ["prize_memory_id_4", 0], ["prize_memory_id_5", 0], ["prize_memory_id_6", 0], ["prize_memory_id_7", 0], ["prize_memory_id_8", 0], ["prize_memory_id_9", 0], ["prizegacha_id", 100147], ["rarity_odds", 100000]]
        ]
      }
    },
    "voice_group": {
      "data_changes": {
        "added": [
          [["group_id", 20206], ["group_id_comment", "琳德＆萊拉耶爾"], ["group_unit_id_01", 127701001], ["group_unit_id_02", 126501001], ["group_unit_id_03", 0], ["group_unit_id_04", 0], ["group_unit_id_05", 0]],
          [["group_id", 20207], ["group_id_comment", "琳德＆克蘿茜"], ["group_unit_id_01", 127701001], ["group_unit_id_02", 126401001], ["group_unit_id_03", 0], ["group_unit_id_04", 0], ["group_unit_id_05", 0]],
          [["group_id", 20208], ["group_id_comment", "琳德＆望"], ["group_unit_id_01", 127701001], ["group_unit_id_02", 102901001], ["group_unit_id_03", 0], ["group_unit_id_04", 0], ["group_unit_id_05", 0]]
        ]
      }
    },
    "gacha_exchange_lineup": {
      "data_changes": {
        "added": [
          [["end_time", "2025/02/17 15:59:59"], ["exchange_id", 350], ["gacha_bonus_id", 1155], ["id", 901], ["pickup_gacha_id", 30350], ["rarity", 3], ["start_time", "2025/02/10 16:00:00"], ["unit_id", 127701]],
          [["end_time", "2025/02/13 15:59:59"], ["exchange_id", 349], ["gacha_bonus_id", 0], ["id", 900], ["pickup_gacha_id", 0], ["rarity", 3], ["start_time", "2025/02/10 16:00:00"], ["unit_id", 127201]]
        ]
      }
    },
    "promotion_bonus": {
      "data_changes": {
        "added": [
          [["accuracy", 0.0], ["atk", 0.0], ["def", 0.0], ["dodge", 0.0], ["energy_recovery_rate", 10.0], ["energy_reduce_rate", 2400.0], ["hp", 0.0], ["hp_recovery_rate", 0.0], ["life_steal", 0.0], ["magic_critical", 0.0], ["magic_def", 0.0], ["magic_penetrate", 0.0], ["magic_str", 0.0], ["physical_critical", 0.0], ["physical_penetrate", 0.0], ["promotion_level", 34], ["unit_id", 127701], ["wave_energy_recovery", 0.0], ["wave_hp_recovery", 0.0]]
        ]
      }
    },
    "unit_rarity": {
      "data_changes": {
        "added": [
          [["accuracy", 0.0], ["accuracy_growth", 0.0], ["atk", 0.0], ["atk_growth", 0.0], ["consume_gold", 30000], ["consume_num", 100], ["def", 3.19], ["def_growth", 0.5], ["dodge", 0.0], ["dodge_growth", 0.0], ["energy_recovery_rate", 0.0], ["energy_recovery_rate_growth", 0.0], ["energy_reduce_rate", 0.0], ["energy_reduce_rate_growth", 0.0], ["hp", 657.9], ["hp_growth", 104.5], ["hp_recovery_rate", 0.0], ["hp_recovery_rate_growth", 0.0], ["life_steal", 0.0], ["life_steal_growth", 0.0], ["magic_critical", 0.0], ["magic_critical_growth", 0.0], ["magic_def", 2.87], ["magic_def_growth", 0.46], ["magic_penetrate", 0.0], ["magic_penetrate_growth", 0.0], ["magic_str", 33.66], ["magic_str_growth", 5.34], ["physical_critical", 0.0], ["physical_critical_growth", 0.0], ["physical_penetrate", 0.0], ["physical_penetrate_growth", 0.0], ["rarity", 3], ["unit_id", 127701], ["unit_material_id", 31277], ["wave_energy_recovery", 0.0], ["wave_energy_recovery_growth", 0.0], ["wave_hp_recovery", 0.0], ["wave_hp_recovery_growth", 0.0]]
        ]
      }
    },
    "ex_equipment_restriction_unit": {
      "data_changes": {
        "added": [
          [["04e4f0fdf4fc4d477354937e52769f0180dfcca07134e926a794f7bccb0f61f8", 127731], ["483c297fb502a7803c898db5af6ec8786453186652c3e79b0b961c5a8d3858bd", 2.0]]
        ]
      }
    },
    "skill_action": {
      "data_changes": {
        "added": [
          [["action_detail_1", 30], ["action_detail_2", 1], ["action_detail_3", 0], ["action_id", 127201201], ["action_type", 10], ["action_value_1", 1.0], ["action_value_2", 40.0], ["action_value_3", 40.0], ["action_value_4", 12.0], ["action_value_5", 0.0], ["action_value_6", 0.0], ["action_value_7", 0.0], ["class_id", 1], ["description", "讓目標夥伴的魔法攻擊力提升{0}"], ["level_up_disp", "魔法攻擊力提升+{0}"], ["target_area", 3], ["target_assignment", 2], ["target_count", 99], ["target_number", 0], ["target_range", 2160], ["target_type", 21]],
          [["action_detail_1", 4], ["action_detail_2", 0], ["action_detail_3", 1], ["action_id", 127700105], ["action_type", 37], ["action_value_1", 0.3], ["action_value_2", 0.3], ["action_value_3", 0.03], ["action_value_4", 0.0], ["action_value_5", 18.5], ["action_value_6", 0.0], ["action_value_7", 410.0], ["class_id", 1], ["description", "展開每秒回復{0}HP的結界"], ["level_up_disp", "每１秒的HP回復量+{0}"], ["target_area", 3], ["target_assignment", 2], ["target_count", 1], ["target_number", 0], ["target_range", 0], ["target_type", 7]],
          [["action_detail_1", 1], ["action_detail_2", 0], ["action_detail_3", 0], ["action_id", 127301201], ["action_type", 1], ["action_value_1", 27.5], ["action_value_2", 27.5], ["action_value_3", 2.2], ["action_value_4", 0.0], ["action_value_5", 0.0], ["action_value_6", 0.0], ["action_value_7", 0.0], ["class_id", 1], ["description", "對敵方單體造成{0}的物理傷害"], ["level_up_disp", "物理傷害+{0}"], ["target_area", 1], ["target_assignment", 1], ["target_count", 1], ["target_number", 0], ["target_range", 2160], ["target_type", 3]],
          [["action_detail_1", 120], ["action_detail_2", 1], ["action_detail_3", 0], ["action_id", 127700103], ["action_type", 10], ["action_value_1", 1.0], ["action_value_2", 10.0], ["action_value_3", 0.0], ["action_value_4", 18.0], ["action_value_5", 0.0], ["action_value_6", 0.0], ["action_value_7", 0.0], ["class_id", 1], ["description", "提升範圍內我方魔法攻擊暴擊時的傷害{0}％"], ["level_up_disp", ""], ["target_area", 2], ["target_assignment", 2], ["target_count", 99], ["target_number", 0], ["target_range", 300], ["target_type", 3]],
          [["action_detail_1", 2], ["action_detail_2", 0], ["action_detail_3", 0], ["action_id", 127201203], ["action_type", 8], ["action_value_1", 1.6], ["action_value_2", 0.0], ["action_value_3", 12.0], ["action_value_4", 0.0], ["action_value_5", 0.0], ["action_value_6", 0.0], ["action_value_7", 0.0], ["class_id", 1], ["description", "使目標的我方行動速度上升"], ["level_up_disp", ""], ["target_area", 3], ["target_assignment", 2], ["target_count", 99], ["target_number", 0], ["target_range", 2160], ["target_type", 21]],
          [["action_detail_1", 120], ["action_detail_2", 1], ["action_detail_3", 0], ["action_id", 127700207], ["action_type", 10], ["action_value_1", 1.0], ["action_value_2", 4.0], ["action_value_3", 0.0], ["action_value_4", 12.0], ["action_value_5", 0.0], ["action_value_6", 0.0], ["action_value_7", 0.0], ["class_id", 1], ["description", ""], ["level_up_disp", ""], ["target_area", 2], ["target_assignment", 2], ["target_count", 99], ["target_number", 0], ["target_range", 300], ["target_type", 3]],
          [["action_detail_1", 30], ["action_detail_2", 1], ["action_detail_3", 0], ["action_id", 127700205], ["action_type", 10], ["action_value_1", 1.0], ["action_value_2", 12.0], ["action_value_3", 12.0], ["action_value_4", 12.0], ["action_value_5", 0.0], ["action_value_6", 0.0], ["action_value_7", 0.0], ["class_id", 1], ["description", ""], ["level_up_disp", ""], ["target_area", 2], ["target_assignment", 2], ["target_count", 99], ["target_number", 0], ["target_range", 300], ["target_type", 3]],
          [["action_detail_1", 1], ["action_detail_2", 0], ["action_detail_3", 0], ["action_id", 127301205], ["action_type", 16], ["action_value_1", 200.0], ["action_value_2", 0.0], ["action_value_3", 0.0], ["action_value_4", 0.0], ["action_value_5", 0.0], ["action_value_6", 0.0], ["action_value_7", 0.0], ["class_id", 1], ["description", "回復自身{0}的TP"], ["level_up_disp", ""], ["target_area", 1], ["target_assignment", 2], ["target_count", 1], ["target_number", 0], ["target_range", 0], ["target_type", 7]],
          [["action_detail_1", 70], ["action_detail_2", 1], ["action_detail_3", 0], ["action_id", 127700206], ["action_type", 10], ["action_value_1", 1.0], ["action_value_2", 50.0], ["action_value_3", 0.0], ["action_value_4", 12.0], ["action_value_5", 0.0], ["action_value_6", 0.0], ["action_value_7", 0.0], ["class_id", 1], ["description", ""], ["level_up_disp", ""], ["target_area", 2], ["target_assignment", 2], ["target_count", 99], ["target_number", 0], ["target_range", 300], ["target_type", 3]],
          [["action_detail_1", 30], ["action_detail_2", 1], ["action_detail_3", 0], ["action_id", 127700302], ["action_type", 10], ["action_value_1", 1.0], ["action_value_2", 12.0], ["action_value_3", 12.0], ["action_value_4", 12.0], ["action_value_5", 0.0], ["action_value_6", 0.0], ["action_value_7", 0.0], ["class_id", 1], ["description", "提升範圍內的我方{0}的魔法攻擊力"], ["level_up_disp", "魔法攻擊力提升+{0}"], ["target_area", 2], ["target_assignment", 2], ["target_count", 99], ["target_number", 0], ["target_range", 300], ["target_type", 3]],
          [["action_detail_1", 40], ["action_detail_2", 1], ["action_detail_3", 0], ["action_id", 127700303], ["action_type", 10], ["action_value_1", 1.0], ["action_value_2", 0.5], ["action_value_3", 0.5], ["action_value_4", 12.0], ["action_value_5", 0.0], ["action_value_6", 0.0], ["action_value_7", 0.0], ["class_id", 1], ["description", "提升範圍內的我方{0}的魔法防禦力"], ["level_up_disp", "魔法防禦力提升+{0}"], ["target_area", 2], ["target_assignment", 2], ["target_count", 99], ["target_number", 0], ["target_range", 300], ["target_type", 3]],
          [["action_detail_1", 120], ["action_detail_2", 1], ["action_detail_3", 0], ["action_id", 127700204], ["action_type", 10], ["action_value_1", 1.0], ["action_value_2", 4.0], ["action_value_3", 0.0], ["action_value_4", 12.0], ["action_value_5", 0.0], ["action_value_6", 0.0], ["action_value_7", 0.0], ["class_id", 1], ["description", "提升範圍內我方魔法攻擊暴擊時的傷害{0}％"], ["level_up_disp", ""], ["target_area", 2], ["target_assignment", 2], ["target_count", 99], ["target_number", 0], ["target_range", 300], ["target_type", 3]],
          [["action_detail_1", 40], ["action_detail_2", 1], ["action_detail_3", 0], ["action_id", 127700307], ["action_type", 10], ["action_value_1", 1.0], ["action_value_2", 0.5], ["action_value_3", 0.5], ["action_value_4", 12.0], ["action_value_5", 0.0], ["action_value_6", 0.0], ["action_value_7", 0.0], ["class_id", 1], ["description", ""], ["level_up_disp", ""], ["target_area", 2], ["target_assignment", 2], ["target_count", 99], ["target_number", 0], ["target_range", 300], ["target_type", 3]],
          [["action_detail_1", 30], ["action_detail_2", 1], ["action_detail_3", 0], ["action_id", 127700101], ["action_type", 10], ["action_value_1", 1.0], ["action_value_2", 30.0], ["action_value_3", 30.0], ["action_value_4", 18.0], ["action_value_5", 0.0], ["action_value_6", 0.0], ["action_value_7", 0.0], ["class_id", 1], ["description", "提升範圍內的我方{0}的魔法攻擊力"], ["level_up_disp", "魔法攻擊力提升+{0}"], ["target_area", 2], ["target_assignment", 2], ["target_count", 99], ["target_number", 0], ["target_range", 300], ["target_type", 3]],
          [["action_detail_1", 1], ["action_detail_2", 0], ["action_detail_3", 0], ["action_id", 127700305], ["action_type", 16], ["action_value_1", 60.0], ["action_value_2", 0.0], ["action_value_3", 0.0], ["action_value_4", 0.0], ["action_value_5", 0.0], ["action_value_6", 0.0], ["action_value_7", 0.0], ["class_id", 1], ["description", "讓範圍內的夥伴恢復{0}TP"], ["level_up_disp", ""], ["target_area", 2], ["target_assignment", 2], ["target_count", 99], ["target_number", 0], ["target_range", 300], ["target_type", 3]],
          [["action_detail_1", 70], ["action_detail_2", 1], ["action_detail_3", 0], ["action_id", 127700102], ["action_type", 10], ["action_value_1", 1.0], ["action_value_2", 100.0], ["action_value_3", 0.0], ["action_value_4", 18.0], ["action_value_5", 0.0], ["action_value_6", 0.0], ["action_value_7", 0.0], ["class_id", 1], ["description", "使範圍內全體夥伴提升{0}的魔法暴擊"], ["level_up_disp", ""], ["target_area", 2], ["target_assignment", 2], ["target_count", 99], ["target_number", 0], ["target_range", 300], ["target_type", 3]],
          [["action_detail_1", 5], ["action_detail_2", 0], ["action_detail_3", 0], ["action_id", 127751101], ["action_type", 90], ["action_value_1", 1.0], ["action_value_2", 32.0], ["action_value_3", 2.0], ["action_value_4", 1.0], ["action_value_5", 0.0], ["action_value_6", 0.0], ["action_value_7", 0.0], ["class_id", 1], ["description", "提升自身{0}的魔法防禦力"], ["level_up_disp", "魔法防禦力提升+{0}"], ["target_area", 0], ["target_assignment", 0], ["target_count", 0], ["target_number", 0], ["target_range", 0], ["target_type", 0]],
          [["action_detail_1", 2], ["action_detail_2", 0], ["action_detail_3", 0], ["action_id", 127700304], ["action_type", 6], ["action_value_1", 32.0], ["action_value_2", 32.0], ["action_value_3", 12.0], ["action_value_4", 0.0], ["action_value_5", 0.0], ["action_value_6", 0.0], ["action_value_7", 0.0], ["class_id", 1], ["description", "展開{0}傷害量的魔法無效護盾"], ["level_up_disp", "無效傷害量+{0}"], ["target_area", 2], ["target_assignment", 2], ["target_count", 99], ["target_number", 0], ["target_range", 300], ["target_type", 3]],
          [["action_detail_1", 70], ["action_detail_2", 1], ["action_detail_3", 0], ["action_id", 127700203], ["action_type", 10], ["action_value_1", 1.0], ["action_value_2", 50.0], ["action_value_3", 0.0], ["action_value_4", 12.0], ["action_value_5", 0.0], ["action_value_6", 0.0], ["action_value_7", 0.0], ["class_id", 1], ["description", "使範圍內全體夥伴提升{0}的魔法暴擊"], ["level_up_disp", ""], ["target_area", 2], ["target_assignment", 2], ["target_count", 99], ["target_number", 0], ["target_range", 300], ["target_type", 3]],
          [["action_detail_1", 60], ["action_detail_2", 1], ["action_detail_3", 0], ["action_id", 127301204], ["action_type", 10], ["action_value_1", 1.0], ["action_value_2", 90.0], ["action_value_3", 0.0], ["action_value_4", 180.0], ["action_value_5", 0.0], ["action_value_6", 0.0], ["action_value_7", 0.0], ["class_id", 1], ["description", "使範圍內所有夥伴提升{0}的物理暴擊"], ["level_up_disp", ""], ["target_area", 2], ["target_assignment", 2], ["target_count", 99], ["target_number", 0], ["target_range", 150], ["target_type", 3]],
          [["action_detail_1", 127700105], ["action_detail_2", 127700306], ["action_detail_3", 0], ["action_id", 127700301], ["action_type", 53], ["action_value_1", 1.0], ["action_value_2", 2.0], ["action_value_3", 0.0], ["action_value_4", 0.0], ["action_value_5", 0.0], ["action_value_6", 0.0], ["action_value_7", 0.0], ["class_id", 1], ["description", "領域展開時，再次發動以下的效果"], ["level_up_disp", ""], ["target_area", 0], ["target_assignment", 0], ["target_count", 0], ["target_number", 0], ["target_range", 0], ["target_type", 0]],
          [["action_detail_1", 30], ["action_detail_2", 1], ["action_detail_3", 0], ["action_id", 127700306], ["action_type", 10], ["action_value_1", 1.0], ["action_value_2", 12.0], ["action_value_3", 12.0], ["action_value_4", 12.0], ["action_value_5", 0.0], ["action_value_6", 0.0], ["action_value_7", 0.0], ["class_id", 1], ["description", ""], ["level_up_disp", ""], ["target_area", 2], ["target_assignment", 2], ["target_count", 99], ["target_number", 0], ["target_range", 300], ["target_type", 3]],
          [["action_detail_1", 1001], ["action_detail_2", 127301203], ["action_detail_3", 0], ["action_id", 127301202], ["action_type", 28], ["action_value_1", 1.0], ["action_value_2", 2.0], ["action_value_3", 0.0], ["action_value_4", 0.0], ["action_value_5", 0.0], ["action_value_6", 0.0], ["action_value_7", 0.0], ["class_id", 1], ["description", ""], ["level_up_disp", ""], ["target_area", 1], ["target_assignment", 1], ["target_count", 1], ["target_number", 0], ["target_range", 2160], ["target_type", 3]],
          [["action_detail_1", 10], ["action_detail_2", 1], ["action_detail_3", 0], ["action_id", 127301203], ["action_type", 10], ["action_value_1", 1.0], ["action_value_2", 24.0], ["action_value_3", 24.0], ["action_value_4", 180.0], ["action_value_5", 0.0], ["action_value_6", 0.0], ["action_value_7", 0.0], ["class_id", 1], ["description", "提升範圍內的我方{0}的物理攻擊力"], ["level_up_disp", "物理攻擊力提升+{0}"], ["target_area", 2], ["target_assignment", 2], ["target_count", 99], ["target_number", 0], ["target_range", 150], ["target_type", 3]],
          [["action_detail_1", 1], ["action_detail_2", 0], ["action_detail_3", 0], ["action_id", 127700309], ["action_type", 16], ["action_value_1", 60.0], ["action_value_2", 0.0], ["action_value_3", 0.0], ["action_value_4", 0.0], ["action_value_5", 0.0], ["action_value_6", 0.0], ["action_value_7", 0.0], ["class_id", 1], ["description", ""], ["level_up_disp", ""], ["target_area", 2], ["target_assignment", 2], ["target_count", 99], ["target_number", 0], ["target_range", 300], ["target_type", 3]],
          [["action_detail_1", 2], ["action_detail_2", 0], ["action_detail_3", 0], ["action_id", 127700104], ["action_type", 4], ["action_value_1", 1.0], ["action_value_2", 4.0], ["action_value_3", 4.0], ["action_value_4", 0.4], ["action_value_5", 0.0], ["action_value_6", 0.0], ["action_value_7", 0.0], ["class_id", 1], ["description", "回復範圍內的我方{0}的HP"], ["level_up_disp", "HP回復量+{0}"], ["target_area", 2], ["target_assignment", 2], ["target_count", 99], ["target_number", 0], ["target_range", 300], ["target_type", 3]],
          [["action_detail_1", 30], ["action_detail_2", 1], ["action_detail_3", 0], ["action_id", 127700202], ["action_type", 10], ["action_value_1", 1.0], ["action_value_2", 12.0], ["action_value_3", 12.0], ["action_value_4", 12.0], ["action_value_5", 0.0], ["action_value_6", 0.0], ["action_value_7", 0.0], ["class_id", 1], ["description", "提升範圍內的我方{0}的魔法攻擊力"], ["level_up_disp", "魔法攻擊力提升+{0}"], ["target_area", 2], ["target_assignment", 2], ["target_count", 99], ["target_number", 0], ["target_range", 300], ["target_type", 3]],
          [["action_detail_1", 5], ["action_detail_2", 0], ["action_detail_3", 0], ["action_id", 127750101], ["action_type", 90], ["action_value_1", 1.0], ["action_value_2", 2.0], ["action_value_3", 2.0], ["action_value_4", 1.0], ["action_value_5", 0.0], ["action_value_6", 0.0], ["action_value_7", 0.0], ["class_id", 1], ["description", "提升自身{0}的魔法防禦力"], ["level_up_disp", "魔法防禦力提升+{0}"], ["target_area", 0], ["target_assignment", 0], ["target_count", 0], ["target_number", 0], ["target_range", 0], ["target_type", 0]],
          [["action_detail_1", 2], ["action_detail_2", 0], ["action_detail_3", 0], ["action_id", 127700308], ["action_type", 6], ["action_value_1", 32.0], ["action_value_2", 32.0], ["action_value_3", 12.0], ["action_value_4", 0.0], ["action_value_5", 0.0], ["action_value_6", 0.0], ["action_value_7", 0.0], ["class_id", 1], ["description", ""], ["level_up_disp", ""], ["target_area", 2], ["target_assignment", 2], ["target_count", 99], ["target_number", 0], ["target_range", 300], ["target_type", 3]],
          [["action_detail_1", 70], ["action_detail_2", 1], ["action_detail_3", 0], ["action_id", 127201202], ["action_type", 10], ["action_value_1", 1.0], ["action_value_2", 120.0], ["action_value_3", 0.0], ["action_value_4", 12.0], ["action_value_5", 0.0], ["action_value_6", 0.0], ["action_value_7", 0.0], ["class_id", 1], ["description", "提升目標夥伴{0}的魔法暴擊"], ["level_up_disp", ""], ["target_area", 3], ["target_assignment", 2], ["target_count", 99], ["target_number", 0], ["target_range", 2160], ["target_type", 21]],
          [["action_detail_1", 127700105], ["action_detail_2", 127700205], ["action_detail_3", 0], ["action_id", 127700201], ["action_type", 53], ["action_value_1", 1.0], ["action_value_2", 2.0], ["action_value_3", 0.0], ["action_value_4", 0.0], ["action_value_5", 0.0], ["action_value_6", 0.0], ["action_value_7", 0.0], ["class_id", 1], ["description", "領域展開時，再次發動以下的效果"], ["level_up_disp", ""], ["target_area", 0], ["target_assignment", 0], ["target_count", 0], ["target_number", 0], ["target_range", 0], ["target_type", 0]]
        ]
      }
    },
    "v1_b457a9eabef0b622409b0ff7c16dcb1fd96ab2b5d52030e80fb318e35141273b": {
      "data_changes": {
        "added": [
          [["0706d88fa0babb93c405c525a2b13083ae8a6cfdbd91cd8cbde5843c2f2350a6", 0], ["2a420e41e4cb4df9001ac03fb6c6609e77f6677f8153f4d9d78717f6c13480f8", "2015/04/01 15:00:00"], ["2aa5b2060b8d357686258614817b39a0583e6d203766f6af2870ec5d7cd0c707", "2030/12/17 14:59:59"], ["348b5672dcbce43788710197fc936dbc7bd4aa8dba199e0c907b289bff774965", 1277], ["5eacdc9525f98bd704e09656f0bb18b0778dd114d3ae1d4e3b8fe13ff1a8bd90", "琳德"], ["6b993a963adaa7daf5639184fbe04203f5b55206d92ebdfeec7fa2b66feaa11c", 0], ["80bb2d5eaf13c30b8406f03918c2f9ee582cd3d95c03fea3e8cd0ae1adae13ee", 1277], ["85afedfcec6c11436e71a30f1a7b4d3d7b505fe7bec2805f720029d957336d70", 1], ["e03b8c2d9f6c69e99cf88133cdcf57f7f670091d47cb50ff9bae78ec1dcf21bc", 263], ["ea9b84af9da6bf97e0d1cb939c868292a32cf42392762da59096b3b12ee9ec71", 819431], ["ef8e7ece28e4c421396e4fb160bfee38e92bfc2b4accf67473c2414a25913f13", 0]]
        ]
      }
    },
    "unit_unique_equipment": {
      "data_changes": {
        "added": [
          [["equip_id", 132731], ["equip_slot", 1], ["unit_id", 127301]],
          [["equip_id", 132721], ["equip_slot", 1], ["unit_id", 127201]]
        ]
      }
    }
  }
}